src/fault_fsm.sv
// src/fault_fsm.sv
// Production-ready Fault FSM with SVA + telemetry counters
module fault_fsm #(
    parameter int NUM_CELLS = 4,
    parameter int ADC_WIDTH = 12,
    parameter int V_WARN = 330,
    parameter int V_FAULT = 300,
    parameter int I_WARN = 150,
    parameter int I_FAULT = 200,
    parameter int T_WARN = 60,
    parameter int T_FAULT = 80,
    parameter int DEBOUNCE_CYCLES = 8,
    parameter int PERSIST_TO_FAULT = 50,
    
    // Local parameters for consistent widths
    localparam int DEBOUNCE_WIDTH = $clog2(DEBOUNCE_CYCLES+1)
) (
    input  logic                          clk,
    input  logic                          rst_n,
    input  logic [(NUM_CELLS*ADC_WIDTH)-1:0] cell_voltage_packed,
    input  logic [ADC_WIDTH-1:0]          current_raw,
    input  logic [ADC_WIDTH-1:0]          temp_raw,
    input  logic                          mask_voltage,
    input  logic                          mask_current,
    input  logic                          mask_temp,
    input  logic                          manual_reset,

    output logic [1:0]                    state_o,
    output logic                          fault_latched_o,
    output logic [1:0]                    active_fault_code_o,
    // telemetry
    output logic [31:0]                   fault_count_o,
    output logic [31:0]                   warning_count_o,
    output logic [31:0]                   last_fault_cycle_o
);

    localparam STATE_NORMAL   = 2'd0;
    localparam STATE_WARNING  = 2'd1;
    localparam STATE_FAULT    = 2'd2;
    localparam STATE_SHUTDOWN = 2'd3;

    // helper to extract cell
    function automatic logic [ADC_WIDTH-1:0] get_cell(input int idx);
        get_cell = cell_voltage_packed[(idx+1)*ADC_WIDTH-1 -: ADC_WIDTH];
    endfunction

    // resolve visible code (priority: TEMP>CURR>VOLT)
    function automatic logic [1:0] resolve_code(input logic v, input logic c, input logic t,
                                                 input logic m_v, input logic m_c, input logic m_t);
        if (t && !m_t) resolve_code = 2'd3;
        else if (c && !m_c) resolve_code = 2'd2;
        else if (v && !m_v) resolve_code = 2'd1;
        else resolve_code = 2'd0;
    endfunction

    // debounce counters & flags
    logic [DEBOUNCE_WIDTH-1:0] cell_cnt [NUM_CELLS];
    logic [DEBOUNCE_WIDTH-1:0] curr_cnt;
    logic [DEBOUNCE_WIDTH-1:0] temp_cnt;
    logic cell_debounced [NUM_CELLS];
    logic curr_debounced;
    logic temp_debounced;

    // FSM regs
    logic [1:0] state_reg, state_nxt;
    logic [31:0] warning_persist_cnt;
    logic fault_latched_reg;
    logic [1:0] active_fault_code_reg;

    // telemetry regs
    logic [31:0] fault_count_reg;
    logic [31:0] warning_count_reg;
    logic [31:0] last_fault_cycle_reg;
    logic [31:0] cycle_counter;

    // simple all-cells aggregate flag (module-scope)
    logic any_cell_deb;
    
    // Current fault code - moved outside always_ff block
    logic [1:0] cur_code;

    int i;
    // debounce synchronous and FSM update
    always_ff @(posedge clk or negedge rst_n) begin
        if (!rst_n) begin
            for (i=0;i<NUM_CELLS;i=i+1) begin
                cell_cnt[i] <= '0;
                cell_debounced[i] <= 1'b0;
            end
            curr_cnt <= '0; temp_cnt <= '0;
            curr_debounced <= 1'b0; temp_debounced <= 1'b0;
            state_reg <= STATE_NORMAL;
            warning_persist_cnt <= 32'd0;
            fault_latched_reg <= 1'b0;
            active_fault_code_reg <= 2'd0;
            fault_count_reg <= 32'd0;
            warning_count_reg <= 32'd0;
            last_fault_cycle_reg <= 32'd0;
            cycle_counter <= 32'd0;
            any_cell_deb <= 1'b0;
        end else begin
            cycle_counter <= cycle_counter + 1;
            // per-cell debounce
            for (i=0;i<NUM_CELLS;i=i+1) begin
                if (get_cell(i) < ADC_WIDTH'(V_WARN))
                    cell_cnt[i] <= (cell_cnt[i] == DEBOUNCE_WIDTH'(DEBOUNCE_CYCLES)) ? cell_cnt[i] : cell_cnt[i] + 1;
                else
                    cell_cnt[i] <= '0;
                cell_debounced[i] <= (cell_cnt[i] >= DEBOUNCE_WIDTH'(DEBOUNCE_CYCLES));
            end
            // current debounce
            if (current_raw > ADC_WIDTH'(I_WARN))
                curr_cnt <= (curr_cnt == DEBOUNCE_WIDTH'(DEBOUNCE_CYCLES)) ? curr_cnt : curr_cnt + 1;
            else curr_cnt <= '0;
            curr_debounced <= (curr_cnt >= DEBOUNCE_WIDTH'(DEBOUNCE_CYCLES));
            // temp debounce
            if (temp_raw > ADC_WIDTH'(T_WARN))
                temp_cnt <= (temp_cnt == DEBOUNCE_WIDTH'(DEBOUNCE_CYCLES)) ? temp_cnt : temp_cnt + 1;
            else temp_cnt <= '0;
            temp_debounced <= (temp_cnt >= DEBOUNCE_WIDTH'(DEBOUNCE_CYCLES));

            // any_cell_deb computation
            any_cell_deb <= 1'b0;
            for (i=0;i<NUM_CELLS;i=i+1) any_cell_deb <= any_cell_deb | cell_debounced[i];

            // resolve visible code
            cur_code = resolve_code(any_cell_deb, curr_debounced, temp_debounced,
                                   mask_voltage, mask_current, mask_temp);

            // FSM next
            state_nxt = state_reg;
            case (state_reg)
                STATE_NORMAL: if (cur_code != 2'd0) begin state_nxt = STATE_WARNING; warning_count_reg <= warning_count_reg + 1; end
                STATE_WARNING: begin
                    if (cur_code == 2'd0) begin
                        if (warning_persist_cnt == 0) state_nxt = STATE_NORMAL;
                        else warning_persist_cnt <= warning_persist_cnt - 1;
                    end else begin
                        warning_persist_cnt <= warning_persist_cnt + 1;
                        if (warning_persist_cnt >= PERSIST_TO_FAULT) begin
                            state_nxt = STATE_FAULT;
                        end
                    end
                end
                STATE_FAULT: begin
                    if (manual_reset) begin
                        state_nxt = STATE_NORMAL;
                    end else if (temp_debounced && !mask_temp) begin
                        state_nxt = STATE_SHUTDOWN;
                    end
                end
                STATE_SHUTDOWN: if (manual_reset) state_nxt = STATE_NORMAL;
            endcase

            // latch and telemetry updates
            if (state_nxt == STATE_FAULT && state_reg != STATE_FAULT) begin
                fault_latched_reg <= 1'b1;
                active_fault_code_reg <= cur_code;
                fault_count_reg <= fault_count_reg + 1;
                last_fault_cycle_reg <= cycle_counter;
            end
            if (state_nxt == STATE_SHUTDOWN) begin
                fault_latched_reg <= 1'b1;
                active_fault_code_reg <= 2'd3;
                fault_count_reg <= fault_count_reg + 1;
                last_fault_cycle_reg <= cycle_counter;
            end
            if (manual_reset) begin
                fault_latched_reg <= 1'b0;
                active_fault_code_reg <= 2'd0;
                warning_persist_cnt <= 32'd0;
            end
            state_reg <= state_nxt;
        end
    end

    // outputs
    assign state_o = state_reg;
    assign fault_latched_o = fault_latched_reg;
    assign active_fault_code_o = active_fault_code_reg;
    assign fault_count_o = fault_count_reg;
    assign warning_count_o = warning_count_reg;
    assign last_fault_cycle_o = last_fault_cycle_reg;

    //-------------------------------------------------
    // Assertions - converted to simple checks for Verilator compatibility
    //-------------------------------------------------
`ifdef ASSERTIONS_ON
    // Check for direct NORMAL->SHUTDOWN transition
    always_ff @(posedge clk) begin
        if (rst_n) begin
            if ($past(state_reg) == STATE_NORMAL && state_reg == STATE_SHUTDOWN) begin
                $error("Assertion failed: direct NORMAL->SHUTDOWN transition detected");
            end
        end
    end

    // Check temp priority
    always_ff @(posedge clk) begin
        if (rst_n) begin
            if (temp_debounced && !mask_temp && fault_latched_reg && active_fault_code_reg != 2'd3) begin
                $error("Assertion failed: temp priority violated");
            end
        end
    end

    // Check latch matches code
    always_ff @(posedge clk) begin
        if (rst_n) begin
            if (fault_latched_reg && (state_reg==STATE_FAULT || state_reg==STATE_SHUTDOWN) && active_fault_code_reg == 2'd0) begin
                $error("Assertion failed: latch without code");
            end
        end
    end
`endif

endmodule

waveforms/tb_fault_fsm.vcd
$version Generated by VerilatedVcd $end
$date Sun Sep 21 22:11:48 2025
 $end
$timescale   1ps $end

 $scope module TOP $end
  $var wire  2 G active_fault_code_o [1:0] $end
  $var wire 48 = cell_voltage_packed [47:0] $end
  $var wire  1 ; clk $end
  $var wire 12 ? current_raw [11:0] $end
  $var wire 32 H fault_count_o [31:0] $end
  $var wire  1 F fault_latched_o $end
  $var wire 32 J last_fault_cycle_o [31:0] $end
  $var wire  1 D manual_reset $end
  $var wire  1 B mask_current $end
  $var wire  1 C mask_temp $end
  $var wire  1 A mask_voltage $end
  $var wire  1 < rst_n $end
  $var wire  2 E state_o [1:0] $end
  $var wire 12 @ temp_raw [11:0] $end
  $var wire 32 I warning_count_o [31:0] $end
  $scope module fault_fsm $end
   $var wire 32 L ADC_WIDTH [31:0] $end
   $var wire 32 S DEBOUNCE_CYCLES [31:0] $end
   $var wire 32 K DEBOUNCE_WIDTH [31:0] $end
   $var wire 32 P I_FAULT [31:0] $end
   $var wire 32 O I_WARN [31:0] $end
   $var wire 32 K NUM_CELLS [31:0] $end
   $var wire 32 T PERSIST_TO_FAULT [31:0] $end
   $var wire  2 W STATE_FAULT [1:0] $end
   $var wire  2 U STATE_NORMAL [1:0] $end
   $var wire  2 X STATE_SHUTDOWN [1:0] $end
   $var wire  2 V STATE_WARNING [1:0] $end
   $var wire 32 R T_FAULT [31:0] $end
   $var wire 32 Q T_WARN [31:0] $end
   $var wire 32 N V_FAULT [31:0] $end
   $var wire 32 M V_WARN [31:0] $end
   $var wire  2 G active_fault_code_o [1:0] $end
   $var wire  2 4 active_fault_code_reg [1:0] $end
   $var wire  1 9 any_cell_deb $end
   $var wire  4 # cell_cnt(0) [3:0] $end
   $var wire  4 $ cell_cnt(1) [3:0] $end
   $var wire  4 % cell_cnt(2) [3:0] $end
   $var wire  4 & cell_cnt(3) [3:0] $end
   $var wire  1 * cell_debounced(0) $end
   $var wire  1 + cell_debounced(1) $end
   $var wire  1 , cell_debounced(2) $end
   $var wire  1 - cell_debounced(3) $end
   $var wire 48 = cell_voltage_packed [47:0] $end
   $var wire  1 ; clk $end
   $var wire  2 : cur_code [1:0] $end
   $var wire  4 ( curr_cnt [3:0] $end
   $var wire  1 . curr_debounced $end
   $var wire 12 ? current_raw [11:0] $end
   $var wire 32 8 cycle_counter [31:0] $end
   $var wire 32 H fault_count_o [31:0] $end
   $var wire 32 5 fault_count_reg [31:0] $end
   $var wire  1 F fault_latched_o $end
   $var wire  1 3 fault_latched_reg $end
   $var wire 32 ' i [31:0] $end
   $var wire 32 J last_fault_cycle_o [31:0] $end
   $var wire 32 7 last_fault_cycle_reg [31:0] $end
   $var wire  1 D manual_reset $end
   $var wire  1 B mask_current $end
   $var wire  1 C mask_temp $end
   $var wire  1 A mask_voltage $end
   $var wire  1 < rst_n $end
   $var wire  2 1 state_nxt [1:0] $end
   $var wire  2 E state_o [1:0] $end
   $var wire  2 0 state_reg [1:0] $end
   $var wire  4 ) temp_cnt [3:0] $end
   $var wire  1 / temp_debounced $end
   $var wire 12 @ temp_raw [11:0] $end
   $var wire 32 I warning_count_o [31:0] $end
   $var wire 32 6 warning_count_reg [31:0] $end
   $var wire 32 2 warning_persist_cnt [31:0] $end
  $upscope $end
 $upscope $end
$enddefinitions $end


#0
b0000 #
b0000 $
b0000 %
b0000 &
b00000000000000000000000000000000 '
b0000 (
b0000 )
0*
0+
0,
0-
0.
0/
b00 0
b00 1
b00000000000000000000000000000000 2
03
b00 4
b00000000000000000000000000000000 5
b00000000000000000000000000000000 6
b00000000000000000000000000000000 7
b00000000000000000000000000000000 8
09
b00 :
0;
0<
b000101101000000101101000000101101000000101101000 =
b000001100100 ?
b000000101000 @
0A
0B
0C
0D
b00 E
0F
b00 G
b00000000000000000000000000000000 H
b00000000000000000000000000000000 I
b00000000000000000000000000000000 J
b00000000000000000000000000000100 K
b00000000000000000000000000001100 L
b00000000000000000000000101001010 M
b00000000000000000000000100101100 N
b00000000000000000000000010010110 O
b00000000000000000000000011001000 P
b00000000000000000000000000111100 Q
b00000000000000000000000001010000 R
b00000000000000000000000000001000 S
b00000000000000000000000000110010 T
b00 U
b01 V
b10 W
b11 X
#5
b00000000000000000000000000000100 '
1;
#10
0;
#15
#20
1;
#25
0;
#30
#35
1;
#40
0;
#45
#50
1;
#55
0;
#60
1<
#65
b00000000000000000000000000000001 8
1;
#70
0;
#75
#80
b00000000000000000000000000000010 8
1;
#85
0;
#90
#95
b00000000000000000000000000000011 8
1;
#100
0;
#105
#110
b00000000000000000000000000000100 8
1;
#115
0;
#120
#125
b00000000000000000000000000000101 8
1;
#130
0;
#135
#140
b00000000000000000000000000000110 8
1;
#145
0;
#150
#155
b00000000000000000000000000000111 8
1;
#160
0;
#165
#170
b00000000000000000000000000001000 8
1;
#175
0;
#180
#185
b00000000000000000000000000001001 8
1;
#190
0;
#195
#200
b00000000000000000000000000001010 8
1;
#205
0;
#210
#215
b00000000000000000000000000001011 8
1;
#220
0;
#225
#230
b00000000000000000000000000001100 8
1;
#235
0;
#240
#245
b00000000000000000000000000001101 8
1;
#250
0;
#255
#260
b00000000000000000000000000001110 8
1;
#265
0;
#270
#275
b00000000000000000000000000001111 8
1;
#280
0;
#285
#290
b00000000000000000000000000010000 8
1;
#295
0;
#300
#305
b00000000000000000000000000010001 8
1;
#310
0;
#315
#320
b00000000000000000000000000010010 8
1;
#325
0;
#330
#335
b00000000000000000000000000010011 8
1;
#340
0;
#345
#350
b00000000000000000000000000010100 8
1;
#355
0;
#360
#365
b00000000000000000000000000010101 8
1;
#370
0;
#375
#380
b00000000000000000000000000010110 8
1;
#385
0;
#390
#395
b00000000000000000000000000010111 8
1;
#400
0;
#405
#410
b00000000000000000000000000011000 8
1;
#415
0;
#420
#425
b00000000000000000000000000011001 8
1;
#430
0;
#435
#440
b00000000000000000000000000011010 8
1;
#445
0;
#450
#455
b00000000000000000000000000011011 8
1;
#460
0;
#465
#470
b00000000000000000000000000011100 8
1;
#475
0;
#480
#485
b00000000000000000000000000011101 8
1;
#490
0;
#495
#500
b00000000000000000000000000011110 8
1;
#505
0;
#510
#515
b00000000000000000000000000011111 8
1;
#520
0;
#525
#530
b00000000000000000000000000100000 8
1;
#535
0;
#540
#545
b00000000000000000000000000100001 8
1;
#550
0;
#555
#560
b00000000000000000000000000100010 8
1;
#565
0;
#570
#575
b00000000000000000000000000100011 8
1;
#580
0;
#585
#590
b00000000000000000000000000100100 8
1;
#595
0;
#600
#605
b00000000000000000000000000100101 8
1;
#610
0;
#615
#620
b00000000000000000000000000100110 8
1;
#625
0;
#630
#635
b00000000000000000000000000100111 8
1;
#640
0;
#645
#650
b00000000000000000000000000101000 8
1;
#655
0;
#660
#665
b00000000000000000000000000101001 8
1;
#670
0;
#675
#680
b00000000000000000000000000101010 8
1;
#685
0;
#690
#695
b00000000000000000000000000101011 8
1;
#700
0;
#705
#710
b00000000000000000000000000101100 8
1;
#715
0;
#720
#725
b00000000000000000000000000101101 8
1;
#730
0;
#735
#740
b00000000000000000000000000101110 8
1;
#745
0;
#750
#755
b00000000000000000000000000101111 8
1;
#760
0;
#765
#770
b00000000000000000000000000110000 8
1;
#775
0;
#780
#785
b00000000000000000000000000110001 8
1;
#790
0;
#795
#800
b00000000000000000000000000110010 8
1;
#805
0;
#810
#815
b00000000000000000000000000110011 8
1;
#820
0;
#825
#830
b00000000000000000000000000110100 8
1;
#835
0;
#840
#845
b00000000000000000000000000110101 8
1;
#850
0;
#855
#860
b00000000000000000000000000110110 8
1;
#865
0;
#870
#875
b00000000000000000000000000110111 8
1;
#880
0;
#885
#890
b00000000000000000000000000111000 8
1;
#895
0;
#900
#905
b00000000000000000000000000111001 8
1;
#910
0;
#915
#920
b00000000000000000000000000111010 8
1;
#925
0;
#930
#935
b00000000000000000000000000111011 8
1;
#940
0;
#945
#950
b00000000000000000000000000111100 8
1;
#955
0;
#960
#965
b00000000000000000000000000111101 8
1;
#970
0;
#975
#980
b00000000000000000000000000111110 8
1;
#985
0;
#990
#995
b00000000000000000000000000111111 8
1;
#1000
0;
#1005
#1010
b00000000000000000000000001000000 8
1;
#1015
0;
#1020
#1025
b00000000000000000000000001000001 8
1;
#1030
0;
#1035
#1040
b00000000000000000000000001000010 8
1;
#1045
0;
#1050
#1055
b00000000000000000000000001000011 8
1;
#1060
0;
#1065
#1070
b00000000000000000000000001000100 8
1;
#1075
0;
#1080
#1085
b00000000000000000000000001000101 8
1;
#1090
0;
#1095
#1100
b00000000000000000000000001000110 8
1;
#1105
0;
#1110
#1115
b00000000000000000000000001000111 8
1;
#1120
0;
#1125
#1130
b00000000000000000000000001001000 8
1;
#1135
0;
#1140
#1145
b00000000000000000000000001001001 8
1;
#1150
0;
#1155
#1160
b00000000000000000000000001001010 8
1;
#1165
0;
#1170
#1175
b00000000000000000000000001001011 8
1;
#1180
0;
#1185
#1190
b00000000000000000000000001001100 8
1;
#1195
0;
#1200
#1205
b00000000000000000000000001001101 8
1;
#1210
0;
#1215
#1220
b00000000000000000000000001001110 8
1;
#1225
0;
#1230
#1235
b00000000000000000000000001001111 8
1;
#1240
0;
#1245
#1250
b00000000000000000000000001010000 8
1;
#1255
0;
#1260
#1265
b00000000000000000000000001010001 8
1;
#1270
0;
#1275
#1280
b00000000000000000000000001010010 8
1;
#1285
0;
#1290
#1295
b00000000000000000000000001010011 8
1;
#1300
0;
#1305
#1310
b00000000000000000000000001010100 8
1;
#1315
0;
#1320
#1325
b00000000000000000000000001010101 8
1;
#1330
0;
#1335
#1340
b00000000000000000000000001010110 8
1;
#1345
0;
#1350
#1355
b00000000000000000000000001010111 8
1;
#1360
0;
#1365
#1370
b00000000000000000000000001011000 8
1;
#1375
0;
#1380
#1385
b00000000000000000000000001011001 8
1;
#1390
0;
#1395
#1400
b00000000000000000000000001011010 8
1;
#1405
0;
#1410
#1415
b00000000000000000000000001011011 8
1;
#1420
0;
#1425
#1430
b00000000000000000000000001011100 8
1;
#1435
0;
#1440
#1445
b00000000000000000000000001011101 8
1;
#1450
0;
#1455
#1460
b00000000000000000000000001011110 8
1;
#1465
0;
#1470
#1475
b00000000000000000000000001011111 8
1;
#1480
0;
#1485
#1490
b00000000000000000000000001100000 8
1;
#1495
0;
#1500
#1505
b00000000000000000000000001100001 8
1;
#1510
0;
#1515
#1520
b00000000000000000000000001100010 8
1;
#1525
0;
#1530
#1535
b00000000000000000000000001100011 8
1;
#1540
0;
#1545
#1550
b00000000000000000000000001100100 8
1;
#1555
0;
#1560
b000101101000000101101000000100100010000101101000 =
#1565
b0001 $
b00000000000000000000000001100101 8
1;
#1570
0;
#1575
#1580
b0010 $
b00000000000000000000000001100110 8
1;
#1585
0;
#1590
#1595
b0011 $
b00000000000000000000000001100111 8
1;
#1600
0;
#1605
#1610
b0100 $
b00000000000000000000000001101000 8
1;
#1615
0;
#1620
b000101101000000101101000000101101000000101101000 =
#1625
b0000 $
b00000000000000000000000001101001 8
1;
#1630
0;
#1635
#1640
b00000000000000000000000001101010 8
1;
#1645
0;
#1650
#1655
b00000000000000000000000001101011 8
1;
#1660
0;
#1665
#1670
b00000000000000000000000001101100 8
1;
#1675
0;
#1680
#1685
b00000000000000000000000001101101 8
1;
#1690
0;
#1695
#1700
b00000000000000000000000001101110 8
1;
#1705
0;
#1710
#1715
b00000000000000000000000001101111 8
1;
#1720
0;
#1725
#1730
b00000000000000000000000001110000 8
1;
#1735
0;
#1740
#1745
b00000000000000000000000001110001 8
1;
#1750
0;
#1755
#1760
b00000000000000000000000001110010 8
1;
#1765
0;
#1770
#1775
b00000000000000000000000001110011 8
1;
#1780
0;
#1785
#1790
b00000000000000000000000001110100 8
1;
#1795
0;
#1800
#1805
b00000000000000000000000001110101 8
1;
#1810
0;
#1815
#1820
b00000000000000000000000001110110 8
1;
#1825
0;
#1830
#1835
b00000000000000000000000001110111 8
1;
#1840
0;
#1845
#1850
b00000000000000000000000001111000 8
1;
#1855
0;
#1860
#1865
b00000000000000000000000001111001 8
1;
#1870
0;
#1875
#1880
b00000000000000000000000001111010 8
1;
#1885
0;
#1890
#1895
b00000000000000000000000001111011 8
1;
#1900
0;
#1905
#1910
b00000000000000000000000001111100 8
1;
#1915
0;
#1920
#1925
b00000000000000000000000001111101 8
1;
#1930
0;
#1935
#1940
b00000000000000000000000001111110 8
1;
#1945
0;
#1950
#1955
b00000000000000000000000001111111 8
1;
#1960
0;
#1965
#1970
b00000000000000000000000010000000 8
1;
#1975
0;
#1980
#1985
b00000000000000000000000010000001 8
1;
#1990
0;
#1995
#2000
b00000000000000000000000010000010 8
1;
#2005
0;
#2010
#2015
b00000000000000000000000010000011 8
1;
#2020
0;
#2025
#2030
b00000000000000000000000010000100 8
1;
#2035
0;
#2040
#2045
b00000000000000000000000010000101 8
1;
#2050
0;
#2055
#2060
b00000000000000000000000010000110 8
1;
#2065
0;
#2070
#2075
b00000000000000000000000010000111 8
1;
#2080
0;
#2085
#2090
b00000000000000000000000010001000 8
1;
#2095
0;
#2100
#2105
b00000000000000000000000010001001 8
1;
#2110
0;
#2115
#2120
b00000000000000000000000010001010 8
1;
#2125
0;
#2130
#2135
b00000000000000000000000010001011 8
1;
#2140
0;
#2145
#2150
b00000000000000000000000010001100 8
1;
#2155
0;
#2160
#2165
b00000000000000000000000010001101 8
1;
#2170
0;
#2175
#2180
b00000000000000000000000010001110 8
1;
#2185
0;
#2190
#2195
b00000000000000000000000010001111 8
1;
#2200
0;
#2205
#2210
b00000000000000000000000010010000 8
1;
#2215
0;
#2220
b000101101000000100011000000101101000000101101000 =
#2225
b0001 %
b00000000000000000000000010010001 8
1;
#2230
0;
#2235
#2240
b0010 %
b00000000000000000000000010010010 8
1;
#2245
0;
#2250
#2255
b0011 %
b00000000000000000000000010010011 8
1;
#2260
0;
#2265
#2270
b0100 %
b00000000000000000000000010010100 8
1;
#2275
0;
#2280
#2285
b0101 %
b00000000000000000000000010010101 8
1;
#2290
0;
#2295
#2300
b0110 %
b00000000000000000000000010010110 8
1;
#2305
0;
#2310
#2315
b0111 %
b00000000000000000000000010010111 8
1;
#2320
0;
#2325
#2330
b1000 %
b00000000000000000000000010011000 8
1;
#2335
0;
#2340
#2345
1,
b00000000000000000000000010011001 8
1;
#2350
0;
#2355
#2360
b00000000000000000000000010011010 8
1;
#2365
0;
#2370
#2375
b00000000000000000000000010011011 8
1;
#2380
0;
#2385
#2390
b00000000000000000000000010011100 8
1;
#2395
0;
#2400
#2405
b00000000000000000000000010011101 8
1;
#2410
0;
#2415
#2420
b00000000000000000000000010011110 8
1;
#2425
0;
#2430
#2435
b00000000000000000000000010011111 8
1;
#2440
0;
#2445
#2450
b00000000000000000000000010100000 8
1;
#2455
0;
#2460
#2465
b00000000000000000000000010100001 8
1;
#2470
0;
#2475
#2480
b00000000000000000000000010100010 8
1;
#2485
0;
#2490
#2495
b00000000000000000000000010100011 8
1;
#2500
0;
#2505
#2510
b00000000000000000000000010100100 8
1;
#2515
0;
#2520
#2525
b00000000000000000000000010100101 8
1;
#2530
0;
#2535
#2540
b00000000000000000000000010100110 8
1;
#2545
0;
#2550
#2555
b00000000000000000000000010100111 8
1;
#2560
0;
#2565
#2570
b00000000000000000000000010101000 8
1;
#2575
0;
#2580
#2585
b00000000000000000000000010101001 8
1;
#2590
0;
#2595
#2600
b00000000000000000000000010101010 8
1;
#2605
0;
#2610
#2615
b00000000000000000000000010101011 8
1;
#2620
0;
#2625
#2630
b00000000000000000000000010101100 8
1;
#2635
0;
#2640
#2645
b00000000000000000000000010101101 8
1;
#2650
0;
#2655
#2660
b00000000000000000000000010101110 8
1;
#2665
0;
#2670
#2675
b00000000000000000000000010101111 8
1;
#2680
0;
#2685
#2690
b00000000000000000000000010110000 8
1;
#2695
0;
#2700
#2705
b00000000000000000000000010110001 8
1;
#2710
0;
#2715
#2720
b00000000000000000000000010110010 8
1;
#2725
0;
#2730
#2735
b00000000000000000000000010110011 8
1;
#2740
0;
#2745
#2750
b00000000000000000000000010110100 8
1;
#2755
0;
#2760
#2765
b00000000000000000000000010110101 8
1;
#2770
0;
#2775
#2780
b00000000000000000000000010110110 8
1;
#2785
0;
#2790
#2795
b00000000000000000000000010110111 8
1;
#2800
0;
#2805
#2810
b00000000000000000000000010111000 8
1;
#2815
0;
#2820
#2825
b00000000000000000000000010111001 8
1;
#2830
0;
#2835
#2840
b00000000000000000000000010111010 8
1;
#2845
0;
#2850
#2855
b00000000000000000000000010111011 8
1;
#2860
0;
#2865
#2870
b00000000000000000000000010111100 8
1;
#2875
0;
#2880
#2885
b00000000000000000000000010111101 8
1;
#2890
0;
#2895
#2900
b00000000000000000000000010111110 8
1;
#2905
0;
#2910
#2915
b00000000000000000000000010111111 8
1;
#2920
0;
#2925
#2930
b00000000000000000000000011000000 8
1;
#2935
0;
#2940
#2945
b00000000000000000000000011000001 8
1;
#2950
0;
#2955
#2960
b00000000000000000000000011000010 8
1;
#2965
0;
#2970
#2975
b00000000000000000000000011000011 8
1;
#2980
0;
#2985
#2990
b00000000000000000000000011000100 8
1;
#2995
0;
#3000
#3005
b00000000000000000000000011000101 8
1;
#3010
0;
#3015
#3020
b00000000000000000000000011000110 8
1;
#3025
0;
#3030
#3035
b00000000000000000000000011000111 8
1;
#3040
0;
#3045
#3050
b00000000000000000000000011001000 8
1;
#3055
0;
#3060
#3065
b00000000000000000000000011001001 8
1;
#3070
0;
#3075
#3080
b00000000000000000000000011001010 8
1;
#3085
0;
#3090
#3095
b00000000000000000000000011001011 8
1;
#3100
0;
#3105
#3110
b00000000000000000000000011001100 8
1;
#3115
0;
#3120
#3125
b00000000000000000000000011001101 8
1;
#3130
0;
#3135
#3140
b00000000000000000000000011001110 8
1;
#3145
0;
#3150
#3155
b00000000000000000000000011001111 8
1;
#3160
0;
#3165
#3170
b00000000000000000000000011010000 8
1;
#3175
0;
#3180
#3185
b00000000000000000000000011010001 8
1;
#3190
0;
#3195
#3200
b00000000000000000000000011010010 8
1;
#3205
0;
#3210
#3215
b00000000000000000000000011010011 8
1;
#3220
0;
#3225
#3230
b00000000000000000000000011010100 8
1;
#3235
0;
#3240
#3245
b00000000000000000000000011010101 8
1;
#3250
0;
#3255
#3260
b00000000000000000000000011010110 8
1;
#3265
0;
#3270
#3275
b00000000000000000000000011010111 8
1;
#3280
0;
#3285
#3290
b00000000000000000000000011011000 8
1;
#3295
0;
#3300
#3305
b00000000000000000000000011011001 8
1;
#3310
0;
#3315
#3320
b00000000000000000000000011011010 8
1;
#3325
0;
#3330
#3335
b00000000000000000000000011011011 8
1;
#3340
0;
#3345
#3350
b00000000000000000000000011011100 8
1;
#3355
0;
#3360
#3365
b00000000000000000000000011011101 8
1;
#3370
0;
#3375
#3380
b00000000000000000000000011011110 8
1;
#3385
0;
#3390
#3395
b00000000000000000000000011011111 8
1;
#3400
0;
#3405
#3410
b00000000000000000000000011100000 8
1;
#3415
0;
#3420
#3425
b00000000000000000000000011100001 8
1;
#3430
0;
#3435
#3440
b00000000000000000000000011100010 8
1;
#3445
0;
#3450
#3455
b00000000000000000000000011100011 8
1;
#3460
0;
#3465
#3470
b00000000000000000000000011100100 8
1;
#3475
0;
#3480
#3485
b00000000000000000000000011100101 8
1;
#3490
0;
#3495
#3500
b00000000000000000000000011100110 8
1;
#3505
0;
#3510
#3515
b00000000000000000000000011100111 8
1;
#3520
0;
#3525
#3530
b00000000000000000000000011101000 8
1;
#3535
0;
#3540
#3545
b00000000000000000000000011101001 8
1;
#3550
0;
#3555
#3560
b00000000000000000000000011101010 8
1;
#3565
0;
#3570
#3575
b00000000000000000000000011101011 8
1;
#3580
0;
#3585
#3590
b00000000000000000000000011101100 8
1;
#3595
0;
#3600
#3605
b00000000000000000000000011101101 8
1;
#3610
0;
#3615
#3620
b00000000000000000000000011101110 8
1;
#3625
0;
#3630
#3635
b00000000000000000000000011101111 8
1;
#3640
0;
#3645
#3650
b00000000000000000000000011110000 8
1;
#3655
0;
#3660
#3665
b00000000000000000000000011110001 8
1;
#3670
0;
#3675
#3680
b00000000000000000000000011110010 8
1;
#3685
0;
#3690
#3695
b00000000000000000000000011110011 8
1;
#3700
0;
#3705
#3710
b00000000000000000000000011110100 8
1;
#3715
0;
#3720
#3725
b00000000000000000000000011110101 8
1;
#3730
0;
#3735
#3740
b00000000000000000000000011110110 8
1;
#3745
0;
#3750
#3755
b00000000000000000000000011110111 8
1;
#3760
0;
#3765
#3770
b00000000000000000000000011111000 8
1;
#3775
0;
#3780
#3785
b00000000000000000000000011111001 8
1;
#3790
0;
#3795
#3800
b00000000000000000000000011111010 8
1;
#3805
0;
#3810
#3815
b00000000000000000000000011111011 8
1;
#3820
0;
#3825
#3830
b00000000000000000000000011111100 8
1;
#3835
0;
#3840
#3845
b00000000000000000000000011111101 8
1;
#3850
0;
#3855
#3860
b00000000000000000000000011111110 8
1;
#3865
0;
#3870
#3875
b00000000000000000000000011111111 8
1;
#3880
0;
#3885
#3890
b00000000000000000000000100000000 8
1;
#3895
0;
#3900
#3905
b00000000000000000000000100000001 8
1;
#3910
0;
#3915
#3920
b00000000000000000000000100000010 8
1;
#3925
0;
#3930
#3935
b00000000000000000000000100000011 8
1;
#3940
0;
#3945
#3950
b00000000000000000000000100000100 8
1;
#3955
0;
#3960
#3965
b00000000000000000000000100000101 8
1;
#3970
0;
#3975
#3980
b00000000000000000000000100000110 8
1;
#3985
0;
#3990
#3995
b00000000000000000000000100000111 8
1;
#4000
0;
#4005
#4010
b00000000000000000000000100001000 8
1;
#4015
0;
#4020
#4025
b00000000000000000000000100001001 8
1;
#4030
0;
#4035
#4040
b00000000000000000000000100001010 8
1;
#4045
0;
#4050
#4055
b00000000000000000000000100001011 8
1;
#4060
0;
#4065
#4070
b00000000000000000000000100001100 8
1;
#4075
0;
#4080
#4085
b00000000000000000000000100001101 8
1;
#4090
0;
#4095
#4100
b00000000000000000000000100001110 8
1;
#4105
0;
#4110
#4115
b00000000000000000000000100001111 8
1;
#4120
0;
#4125
#4130
b00000000000000000000000100010000 8
1;
#4135
0;
#4140
#4145
b00000000000000000000000100010001 8
1;
#4150
0;
#4155
#4160
b00000000000000000000000100010010 8
1;
#4165
0;
#4170
#4175
b00000000000000000000000100010011 8
1;
#4180
0;
#4185
#4190
b00000000000000000000000100010100 8
1;
